tellyget/__init__.py
tellyget/auth.py
tellyget/generator.py
tellyget/guide.py
tellyget/tellyget.py
tellyget/tellyget_config.py
tellyget/tellyget_decrypt.py
tellyget/utils/__init__.py
tellyget/utils/authenticator.py
tellyget/utils/cipher.py
tellyget/utils/command.py
tellyget/utils/tshark.py
tellyget-1.0.0.dist-info/LICENSE
tellyget-1.0.0.dist-info/METADATA
tellyget-1.0.0.dist-info/WHEEL
tellyget-1.0.0.dist-info/entry_points.txt
tellyget-1.0.0.dist-info/top_level.txt
tellyget-1.0.0.dist-info/RECORD
